pnb/mcl/utils.py
pnb/mcl/convert/dexpi_1_4.py
pnb/mcl/io/rdf.py
pnb/mcl/io/xmi.py
pnb/mcl/io/xml.py
pnb/mcl/metamodel/standard.py
pnb/mcl/test/examples/ex_1.py
pnb/mcl/test/examples/ex_primitive_types.py
pnb/mcl/test/io_rdf/__init__.py
pnb/mcl/test/io_rdf/rdf_exporter.py
pnb/mcl/test/io_xml/__init__.py
pnb/mcl/test/io_xml/xml_exporter.py
pnb/mcl/test/io_xml/xml_importer.py
pnb/mcl/test/model_api/__init__.py
pnb/mcl/test/model_api/enumerations.py
pnb/mcl/test/model_api/properties.py
pnb/mcl/test/model_api/simple_members.py
pnb/mcl/test/model_standard/__init__.py
pnb/mcl/test/model_standard/api.py
pnb/mcl/test/model_standard/internals.py
pnb/mcl/test/utils/__init__.py
pnb/mcl/test/utils/checks.py
pnb_mcl-0.1.8.dist-info/licenses/LICENSE
pnb_mcl-0.1.8.dist-info/METADATA
pnb_mcl-0.1.8.dist-info/WHEEL
pnb_mcl-0.1.8.dist-info/top_level.txt
pnb_mcl-0.1.8.dist-info/RECORD
