Metadata-Version: 2.4
Name: pnb.mcl
Version: 0.1.8
Summary: Easy handling of domain models.
Author-email: pnb plants & bytes GmbH <info@plants-and-bytes.de>
Project-URL: Documentation, https://software.plants-and-bytes.de/pnb.mcl/0.1
Project-URL: Repository, https://github.com/pnb-plants-and-bytes/pnb.mcl
Classifier: Programming Language :: Python :: 3
Classifier: License :: OSI Approved :: MIT License
Classifier: Operating System :: OS Independent
Requires-Python: >=3.12
License-File: LICENSE
Requires-Dist: rdflib>=7.1
Requires-Dist: lxml>=5.3
Dynamic: license-file
